AUTHORS
ChangeLog
MANIFEST.in
README.rst
requirements.txt
setup.cfg
setup.py
leonardo_store_cash_on_delivery.egg-info/PKG-INFO
leonardo_store_cash_on_delivery.egg-info/SOURCES.txt
leonardo_store_cash_on_delivery.egg-info/dependency_links.txt
leonardo_store_cash_on_delivery.egg-info/not-zip-safe
leonardo_store_cash_on_delivery.egg-info/pbr.json
leonardo_store_cash_on_delivery.egg-info/requires.txt
leonardo_store_cash_on_delivery.egg-info/top_level.txt
leonardo_store_cod/__init__.py
leonardo_store_cod/admin.py
leonardo_store_cod/resources.py